LICENSE
MANIFEST.in
README.rst
setup.py
functastic/__init__.py
functastic/functastic.py
functastic.egg-info/PKG-INFO
functastic.egg-info/SOURCES.txt
functastic.egg-info/dependency_links.txt
functastic.egg-info/top_level.txt