Metadata-Version: 1.1
Name: functastic
Version: 1.0.1
Summary: threadable task retry module
Home-page: https://github.com/tr3buchet/functastic
Author: Trey Morris
Author-email: trey@treymorris.com
License: Apache Software License
Keywords: task,tasks,retry,func,functions
Platform: UNKNOWN
Classifier: Development Status :: 5 - Production/Stable
Classifier: License :: OSI Approved :: Apache Software License
